itsai/aspire/__init__.py
itsai/aspire/app.py
itsai/aspire/py.typed
itsai/aspire/datastore/__init__.py
itsai/aspire/datastore/azure_ai_search.py
itsai/aspire/datastore/databricks.py
itsai/aspire/scripts/etl.py
itsai/aspire/scripts/main.py
itsai/aspire/scripts/setup.py
itsai/aspire/vanna/__init__.py
itsai/aspire/vanna/utils.py
itsai/aspire/vanna/base/__init__.py
itsai/aspire/vanna/base/base.py
itsai/aspire/vanna/exceptions/__init__.py
itsai/aspire/vanna/flask/__init__.py
itsai/aspire/vanna/flask/_api.py
itsai/aspire/vanna/flask/_app.py
itsai/aspire/vanna/flask/_cache.py
itsai/aspire/vanna/flask/assets.py
itsai/aspire/vanna/flask/auth.py
itsai/aspire/vanna/openai/__init__.py
itsai/aspire/vanna/openai/openai_chat.py
itsai/aspire/vanna/openai/openai_embeddings.py
itsai/aspire/vanna/types/__init__.py
itsai_aspire-0.1.9.dist-info/METADATA
itsai_aspire-0.1.9.dist-info/WHEEL
itsai_aspire-0.1.9.dist-info/top_level.txt
itsai_aspire-0.1.9.dist-info/RECORD
